mt/uv/__init__.py
mt/uv/version.py
mtuv-0.0.3.data/scripts/pipi
mtuv-0.0.3.dist-info/licenses/LICENSE
mtuv-0.0.3.dist-info/METADATA
mtuv-0.0.3.dist-info/WHEEL
mtuv-0.0.3.dist-info/top_level.txt
mtuv-0.0.3.dist-info/RECORD
