Metadata-Version: 2.4
Name: mtuv
Version: 0.0.3
Summary: Wrapper for Python packaging tooling uv and uv-publish
Home-page: https://github.com/inteplus/mtuv
Author: ['Minh-Tri Pham']
License: MIT
Project-URL: Documentation, https://mtdoc.readthedocs.io/en/latest/mt.uv/mt.uv.html
Project-URL: Source Code, https://github.com/inteplus/mtuv
Requires-Python: >=3.6
License-File: LICENSE
Requires-Dist: uv
Requires-Dist: uv-publish
Requires-Dist: packaging
Dynamic: author
Dynamic: home-page
Dynamic: license
Dynamic: license-file
Dynamic: project-url
Dynamic: requires-dist
Dynamic: requires-python
Dynamic: summary
